zebedee/__init__.py
zebedee/main.py
zebedee-0.1.3.dist-info/LICENSE
zebedee-0.1.3.dist-info/METADATA
zebedee-0.1.3.dist-info/WHEEL
zebedee-0.1.3.dist-info/top_level.txt
zebedee-0.1.3.dist-info/RECORD
