Metadata-Version: 2.1
Name: zebedee
Version: 0.1.3
Summary: Move Money at the Speed of the Internet 
Author: zantoshi (Santos Hernandez)
Author-email: <santos@zebedee.io>
Keywords: python,payments,bitcoin,lightning network,django,lightning
Classifier: Development Status :: 4 - Beta
Classifier: Intended Audience :: Developers
Classifier: Programming Language :: Python :: 3
Classifier: Operating System :: Unix
Classifier: Operating System :: MacOS :: MacOS X
Classifier: Operating System :: Microsoft :: Windows
License-File: LICENSE
Requires-Dist: certifi
Requires-Dist: charset-normalizer
Requires-Dist: idna
Requires-Dist: requests
Requires-Dist: urllib3
